mycroft_precise-0.2.0.dist-info/METADATA
mycroft_precise-0.2.0.dist-info/RECORD
mycroft_precise-0.2.0.dist-info/WHEEL
mycroft_precise-0.2.0.dist-info/entry_points.txt
mycroft_precise-0.2.0.dist-info/top_level.txt
mycroft_precise-0.2.0.dist-info/zip-safe
precise/__init__.py
precise/functions.py
precise/model.py
precise/network_runner.py
precise/params.py
precise/train_data.py
precise/util.py
precise/vectorization.py
precise/pocketsphinx/__init__.py
precise/pocketsphinx/listener.py
precise/pocketsphinx/scripts/__init__.py
precise/pocketsphinx/scripts/listen.py
precise/pocketsphinx/scripts/test.py
precise/scripts/collect.py
precise/scripts/convert.py
precise/scripts/engine.py
precise/scripts/eval.py
precise/scripts/listen.py
precise/scripts/test.py
precise/scripts/train.py
precise/scripts/train_incremental.py
